project_to_markdown/__init__.py
project_to_markdown/markdown_to_project.py
project_to_markdown/project_to_markdown.py
project_to_markdown-0.1.6.dist-info/METADATA
project_to_markdown-0.1.6.dist-info/WHEEL
project_to_markdown-0.1.6.dist-info/entry_points.txt
project_to_markdown-0.1.6.dist-info/top_level.txt
project_to_markdown-0.1.6.dist-info/RECORD
