Metadata-Version: 2.4
Name: project-to-markdown
Version: 0.1.6
Summary: Export a Python project into a single Markdown file.
Author-email: Benaya Trabelsi <benaya7@email.com>
License-Expression: MIT
Project-URL: Homepage, https://github.com/benayat/codebase_to_markdown
Project-URL: Bug Tracker, https://github.com/benayat/codebase_to_markdown/issues
Requires-Python: >=3.7
